embedbuilder/__init__.py
embedbuilder/core.py
embedbuilder/customization.py
embedbuilder/messagesender.py
embedbuilder/pagination.py
embedbuilder/utils.py
py_embedbuilder-0.1.12.dist-info/licenses/LICENSE
py_embedbuilder-0.1.12.dist-info/METADATA
py_embedbuilder-0.1.12.dist-info/WHEEL
py_embedbuilder-0.1.12.dist-info/top_level.txt
py_embedbuilder-0.1.12.dist-info/RECORD
